imptracker/__main__.py
imptracker/_base.py
imptracker/__init__.py
imptracker-0.1.dist-info/WHEEL
imptracker-0.1.dist-info/METADATA
imptracker-0.1.dist-info/RECORD
imptracker-0.1.dist-info/metadata.json
imptracker-0.1.dist-info/DESCRIPTION.rst
imptracker-0.1.dist-info/top_level.txt
