Metadata-Version: 2.0
Name: imptracker
Version: 0.1
Summary: Import Tracker: Find actual imports during runtime
Home-page: UNKNOWN
Author: Torsten Landschoff
Author-email: torsten@landschoff.net
License: UNKNOWN
Platform: UNKNOWN
